{
  "_id": "697d0c6a20af25087693e75a",
  "Timestamp": {
    "Year": "26",
    "Month": "01",
    "Day": "09",
    "Hour": "14",
    "Minute": "03",
    "Second": "47",
    "Centisecond": "92"
  },
  "n_registro": 41,
  "#bins": 53,
  "Depth": 21293,
  "Dmean": 151,
  "Dp": 160,
  "H1/10": 0.16,
  "Hs": 0.13,
  "Profile": [
    {
      "Magnitude": 0.049,
      "Direction": 167
    },
    {
      "Magnitude": 0.031,
      "Direction": 151
    },
    {
      "Magnitude": 0.032,
      "Direction": 152
    },
    {
      "Magnitude": 0.039,
      "Direction": 168
    },
    {
      "Magnitude": 0.024,
      "Direction": 189
    },
    {
      "Magnitude": 0.024,
      "Direction": 195
    },
    {
      "Magnitude": 0.021,
      "Direction": 205
    },
    {
      "Magnitude": 0.036,
      "Direction": 177
    },
    {
      "Magnitude": 0.024,
      "Direction": 192
    },
    {
      "Magnitude": 0.025,
      "Direction": 201
    },
    {
      "Magnitude": 0.027,
      "Direction": 186
    },
    {
      "Magnitude": 0.031,
      "Direction": 211
    },
    {
      "Magnitude": 0.033,
      "Direction": 205
    },
    {
      "Magnitude": 0.026,
      "Direction": 173
    },
    {
      "Magnitude": 0.028,
      "Direction": 190
    },
    {
      "Magnitude": 0.026,
      "Direction": 173
    },
    {
      "Magnitude": 0.025,
      "Direction": 175
    },
    {
      "Magnitude": 0.011,
      "Direction": 124
    },
    {
      "Magnitude": 0.004,
      "Direction": 135
    },
    {
      "Magnitude": 0.018,
      "Direction": 41
    },
    {
      "Magnitude": 0.017,
      "Direction": 62
    },
    {
      "Magnitude": 0.024,
      "Direction": 55
    },
    {
      "Magnitude": 0.035,
      "Direction": 59
    },
    {
      "Magnitude": 0.039,
      "Direction": 66
    },
    {
      "Magnitude": 0.041,
      "Direction": 72
    },
    {
      "Magnitude": 0.044,
      "Direction": 67
    },
    {
      "Magnitude": 0.026,
      "Direction": 65
    },
    {
      "Magnitude": 0.034,
      "Direction": 63
    },
    {
      "Magnitude": 0.027,
      "Direction": 62
    },
    {
      "Magnitude": 0.036,
      "Direction": 66
    },
    {
      "Magnitude": 0.038,
      "Direction": 79
    },
    {
      "Magnitude": 0.044,
      "Direction": 89
    },
    {
      "Magnitude": 0.041,
      "Direction": 108
    },
    {
      "Magnitude": 0.044,
      "Direction": 106
    },
    {
      "Magnitude": 0.045,
      "Direction": 111
    },
    {
      "Magnitude": 0.058,
      "Direction": 125
    },
    {
      "Magnitude": 0.049,
      "Direction": 129
    },
    {
      "Magnitude": 0.122,
      "Direction": 126
    },
    {
      "Magnitude": 0.201,
      "Direction": 161
    },
    {
      "Magnitude": 0.47,
      "Direction": 166
    },
    {
      "Magnitude": 0.495,
      "Direction": 163
    },
    {
      "Magnitude": 0.412,
      "Direction": 183
    },
    {
      "Magnitude": 0.199,
      "Direction": 171
    },
    {
      "Magnitude": 0.119,
      "Direction": 151
    },
    {
      "Magnitude": 0.103,
      "Direction": 148
    },
    {
      "Magnitude": 0.097,
      "Direction": 153
    },
    {
      "Magnitude": 0.115,
      "Direction": 152
    },
    {
      "Magnitude": 0.124,
      "Direction": 156
    },
    {
      "Magnitude": 0.123,
      "Direction": 161
    },
    {
      "Magnitude": 0.113,
      "Direction": 152
    },
    {
      "Magnitude": 0.116,
      "Direction": 159
    },
    {
      "Magnitude": 0.12,
      "Direction": 149
    },
    {
      "Magnitude": -32768,
      "Direction": -32768
    }
  ],
  "Tmean": 13.4,
  "Tp": 12.1
}